__init__.py
formantic-0.1.0.dist-info/METADATA
formantic-0.1.0.dist-info/WHEEL
formantic-0.1.0.dist-info/entry_points.txt
formantic-0.1.0.dist-info/licenses/LICENSE.md
formantic.py
formantic-0.1.0.dist-info/RECORD
