Metadata-Version: 2.1
Name: formantic
Version: 0.1.0
Summary: WTForm generator for Pydantic
Author-Email: Wojciech Nowicki <wnowicki@me.com>
License: # MIT License
Project-URL: Homepage, https://github.com/wnowicki/formantic
Project-URL: Source, https://github.com/wnowicki/formantic
Requires-Python: >=3.10
Requires-Dist: pydantic>=2.11.5
Requires-Dist: wtforms<3.2,>=3.1
